{
  "$schema": "http://json-schema.org/draft-07/schema#",
  "$id": "https://protocol.isimip.org/schema/schema/ISIMIP2a/OutputData/biomes.json",
  "commit": "bd3bc36d8152ca4db22531e40b8e9e1acf4842e9",
  "type": "object",
  "required": [
    "specifiers"
  ],
  "properties": {
    "specifiers": {
      "type": "object",
      "required": [
        "model",
        "climate_forcing",
        "bias_adjustment",
        "climate_scenario",
        "soc_scenario",
        "sens_scenario",
        "variable",
        "region",
        "time_step"
      ],
      "properties": {
        "model": {
          "type": "string"
        },
        "climate_forcing": {
          "type": "string",
          "enum": [
            "watch-wfdei",
            "gswp3-w5e5",
            "princeton",
            "watch",
            "gswp3-ewembi",
            "gswp3",
            "ewembi"
          ]
        },
        "bias_adjustment": {
          "type": "string",
          "enum": [
            "nobc",
            "ewembi"
          ]
        },
        "climate_scenario": {
          "type": "string",
          "enum": [
            "fore",
            "hist"
          ]
        },
        "soc_scenario": {
          "type": "string",
          "enum": [
            "rcp60soca",
            "rcp85soc",
            "rcp85socbe",
            "rcp60socbeb",
            "rcp85soca",
            "rcp85socam",
            "ssp4soc",
            "ssp3soc",
            "varsoc",
            "rcp26socbeb",
            "rcp60socbe",
            "rcp85socbeb",
            "rcp26socam",
            "pressoc",
            "rcp60sochwp",
            "ssp1soc",
            "nat",
            "rcp26soc",
            "rcp60socam",
            "ssp2soc",
            "2005socsite",
            "rcp85sochwp",
            "nosoc",
            "rcp60soc",
            "2100rcp26soc",
            "rcp26soca",
            "histsoc",
            "1860soc",
            "2005soc",
            "ssp5soc",
            "rcp26socbe",
            "rcp26sochwp"
          ]
        },
        "sens_scenario": {
          "type": "string",
          "enum": [
            "default",
            "co2const",
            "co2",
            "2005co2",
            "noco2"
          ]
        },
        "variable": {
          "type": "string",
          "enum": [
            "albedo",
            "croot",
            "npplandleaf",
            "esoil",
            "evap",
            "qsb",
            "soilmoist",
            "clitter",
            "nppbgwood",
            "nppbelowgroundwood",
            "npp",
            "fapar",
            "npproot",
            "swe",
            "tslmax",
            "cvegag",
            "qtot",
            "somcfire",
            "csoil",
            "nppabovegroundwood",
            "rainf",
            "gpp",
            "burntarea",
            "tsl",
            "nppagwood",
            "fireint",
            "rh",
            "soilmoistfroz",
            "lai",
            "npplandroot",
            "qs",
            "snd",
            "thawdepth",
            "ra",
            "pft",
            "cvegbg",
            "firefrac",
            "dis",
            "cleaf",
            "nppleaf",
            "cveg",
            "cwood",
            "rr",
            "potevap",
            "trans",
            "ecoatmflux",
            "pft2storeys",
            "intercep"
          ]
        },
        "pft": {
          "type": "string"
        },
        "crop": {
          "type": "string",
          "enum": [
            "sun",
            "pot",
            "ric",
            "rap",
            "cot",
            "pea",
            "sug",
            "pop",
            "rye",
            "ben",
            "ri2",
            "mil",
            "mai",
            "sgb",
            "sor",
            "whe",
            "ri1",
            "nut",
            "mgr",
            "euc",
            "cas",
            "soy",
            "mis",
            "bar"
          ]
        },
        "irrigation": {
          "type": "string",
          "enum": [
            "noirr"
          ]
        },
        "region": {
          "type": "string",
          "enum": [
            "global",
            "lena",
            "finland"
          ]
        },
        "time_step": {
          "type": "string",
          "enum": [
            "monthly",
            "annual",
            "daily",
            "constant"
          ]
        },
        "start_year": {
          "type": "number"
        },
        "end_year": {
          "type": "number"
        }
      }
    }
  }
}