{
  "$schema": "http://json-schema.org/draft-07/schema#",
  "$id": "https://protocol.isimip.org/schema/schema/ISIMIP2a/OutputData/marine-fishery_global.json",
  "commit": "52338dd2aa4c5e2c14320914413a6cb735a3fc14",
  "type": "object",
  "required": [
    "specifiers"
  ],
  "properties": {
    "specifiers": {
      "type": "object",
      "required": [
        "model",
        "climate_forcing",
        "bias_adjustment",
        "climate_scenario",
        "variable",
        "region",
        "time_step"
      ],
      "properties": {
        "model": {
          "type": "string"
        },
        "climate_forcing": {
          "type": "string",
          "enum": [
            "princeton",
            "gswp3-w5e5",
            "gfdl-reanalysis",
            "key-run",
            "watch",
            "watch-wfdei",
            "gswp3",
            "ewembi",
            "gswp3-ewembi"
          ]
        },
        "bias_adjustment": {
          "type": "string",
          "enum": [
            "ewembi",
            "nobc"
          ]
        },
        "climate_scenario": {
          "type": "string",
          "enum": [
            "fore",
            "hist"
          ]
        },
        "variable": {
          "type": "string",
          "enum": [
            "bsmall",
            "clarge",
            "b30cm-bendet",
            "b10cm-pelpred",
            "tc",
            "cmed",
            "csmall",
            "bcom",
            "b10cm",
            "b10cm-bendet",
            "tc10cm",
            "tcb",
            "tc30cm",
            "tsb",
            "b30cm",
            "blarge",
            "bmed",
            "b30cm-pelpred",
            "tpb"
          ]
        },
        "region": {
          "type": "string",
          "enum": [
            "global"
          ]
        },
        "time_step": {
          "type": "string",
          "enum": [
            "monthly",
            "annual",
            "daily"
          ]
        },
        "start_year": {
          "type": "number"
        },
        "end_year": {
          "type": "number"
        }
      }
    }
  }
}