[
  {
    "sectors": [
      "water_global"
    ],
    "specifier": "admeluse",
    "units": "kg m-2 s-1"
  },
  {
    "long_name": "Actual Domestic Water Consumption",
    "sectors": [
      "water_global"
    ],
    "specifier": "adomuse",
    "units": "kg m-2 s-1",
    "valid_max": 0.002,
    "valid_min": 0.0
  },
  {
    "long_name": "Actual Domestic Water Withdrawal",
    "sectors": [
      "water_global"
    ],
    "specifier": "adomww",
    "units": "kg m-2 s-1",
    "valid_max": 0.002,
    "valid_min": 0.0
  },
  {
    "long_name": "Actual Evapotranspiration",
    "sectors": [
      "agriculture"
    ],
    "specifier": "aet",
    "units": "mm per growing season"
  },
  {
    "long_name": "Actual Industrial Water Consumption",
    "sectors": [
      "water_global"
    ],
    "specifier": "ainduse",
    "units": "kg m-2 s-1",
    "valid_max": 0.002,
    "valid_min": 0.0
  },
  {
    "long_name": "Actual Industrial Water Withdrawal",
    "sectors": [
      "water_global"
    ],
    "specifier": "aindww",
    "units": "kg m-2 s-1",
    "valid_max": 0.002,
    "valid_min": 0.0
  },
  {
    "long_name": "Actual Irrigation Water Consumption",
    "sectors": [
      "water_global",
      "water_regional"
    ],
    "specifier": "airruse",
    "units": "kg m-2 s-1",
    "valid_max": 0.002,
    "valid_min": 0.0
  },
  {
    "long_name": "Actual Irrigation Green Water Consumption on Irrigated Cropland",
    "sectors": [
      "water_global"
    ],
    "specifier": "airrusegreen",
    "units": "kg m-2 s-1",
    "valid_max": 0.002,
    "valid_min": 0.0
  },
  {
    "long_name": "Actual Irrigation Water Withdrawal",
    "sectors": [
      "water_global",
      "water_regional"
    ],
    "specifier": "airrww",
    "units": "kg m-2 s-1",
    "valid_max": 0.002,
    "valid_min": 0.0
  },
  {
    "dimensions": [
      "time",
      "dbhclass",
      "lat",
      "lon"
    ],
    "long_name": "Tree Age by DBH-Class",
    "sectors": [
      "forestry"
    ],
    "specifier": "age",
    "units": "yr"
  },
  {
    "sectors": [
      "lakes_global",
      "lakes_local",
      "biomes"
    ],
    "specifier": "albedo",
    "units": "1"
  },
  {
    "long_name": "Actual livestock Water Consumption",
    "sectors": [
      "water_global"
    ],
    "specifier": "aliveuse",
    "units": "kg m-2 s-1",
    "valid_max": 0.002,
    "valid_min": 0.0
  },
  {
    "long_name": "Actual Livestock Water Withdrawal",
    "sectors": [
      "water_global"
    ],
    "specifier": "aliveww",
    "units": "kg m-2 s-1",
    "valid_max": 0.002,
    "valid_min": 0.0
  },
  {
    "long_name": "Actual Manufacturing Water Consumption",
    "sectors": [
      "water_global"
    ],
    "specifier": "amanuse",
    "units": "kg m-2 s-1",
    "valid_max": 0.002,
    "valid_min": 0.0
  },
  {
    "long_name": "Actual Manufacturing Water Withdrawal",
    "sectors": [
      "water_global"
    ],
    "specifier": "amanww",
    "units": "kg m-2 s-1",
    "valid_max": 0.002,
    "valid_min": 0.0
  },
  {
    "long_name": "Amphibian Species Richness",
    "sectors": [
      "biodiversity"
    ],
    "specifier": "amphibiansr",
    "units": "Estimated number of species (species richness) per cell"
  },
  {
    "long_name": "Amphibian Summed Probability of Occurrence",
    "sectors": [
      "biodiversity"
    ],
    "specifier": "amphibiansumprob",
    "units": "Summed probability of occurrence per cell"
  },
  {
    "long_name": "Anthesis Date",
    "sectors": [
      "agriculture"
    ],
    "specifier": "anthday",
    "units": "day of year of anthesis"
  },
  {
    "long_name": "Actual Green Water Consumption on Rainfed Cropland",
    "sectors": [
      "water_global"
    ],
    "specifier": "arainfusegreen",
    "units": "kg m-2 s-1",
    "valid_max": 0.002,
    "valid_min": 0.0
  },
  {
    "long_name": "Total Actual Water Consumption (all sectors)",
    "sectors": [
      "water_global"
    ],
    "specifier": "atotuse",
    "units": "kg m-2 s-1",
    "valid_max": 0.002,
    "valid_min": 0.0
  },
  {
    "long_name": "Biomass Density of Consumers >10cm ",
    "sectors": [
      "marine-fishery_global",
      "marine-fishery_regional"
    ],
    "specifier": "b10cm",
    "units": "g C m-2"
  },
  {
    "long_name": "Biomass Density of Consumers >30cm",
    "sectors": [
      "marine-fishery_global",
      "marine-fishery_regional"
    ],
    "specifier": "b30cm",
    "units": "g C m-2"
  },
  {
    "long_name": "Basal Area",
    "sectors": [
      "forestry"
    ],
    "specifier": "ba",
    "units": "m2 ha-1"
  },
  {
    "long_name": "Biomass Density of Commercial Species ",
    "sectors": [
      "marine-fishery_global",
      "marine-fishery_regional"
    ],
    "specifier": "bcom",
    "units": "g C m-2"
  },
  {
    "long_name": "Total Above Ground Biomass Dry Matter Yields",
    "sectors": [
      "agriculture"
    ],
    "specifier": "biom",
    "units": "t ha-1 per growing season"
  },
  {
    "long_name": "Terrestrial Bird Species Probability of Occurrence",
    "sectors": [
      "biodiversity"
    ],
    "specifier": "birdprob",
    "units": "Probability of occurrence per cell"
  },
  {
    "long_name": "Terrestrial Bird Species Richness",
    "sectors": [
      "biodiversity"
    ],
    "specifier": "birdsr",
    "units": "Estimated number of species (species richness) per cell"
  },
  {
    "long_name": "Terrestrial Bird Summed Probability of Occurrence ",
    "sectors": [
      "biodiversity"
    ],
    "specifier": "birdsumprob",
    "units": "Summed probability of occurrence per cell"
  },
  {
    "long_name": "Biomass Density of Large Consumers >90cm and <100kg",
    "sectors": [
      "marine-fishery_global"
    ],
    "specifier": "blarge",
    "units": "g C m-2"
  },
  {
    "long_name": "Temperature of Lake Bottom Water",
    "sectors": [
      "lakes_global",
      "lakes_local"
    ],
    "specifier": "bottemp",
    "units": "K"
  },
  {
    "long_name": "Biomass Density of Medium Consumers >30cm and <90cm",
    "sectors": [
      "marine-fishery_global"
    ],
    "specifier": "bmed",
    "units": "g C m-2"
  },
  {
    "long_name": "Biomass Density of Small Consumers <30cm",
    "sectors": [
      "marine-fishery_global"
    ],
    "specifier": "bsmall",
    "units": "g C m-2"
  },
  {
    "long_name": "Burnt Area Fraction",
    "sectors": [
      "permafrost",
      "biomes"
    ],
    "specifier": "burntarea",
    "units": "%"
  },
  {
    "long_name": "Buoyancy frequency",
    "sectors": [
      "lakes_global",
      "lakes_local"
    ],
    "specifier": "buoyancyfrequency",
    "units": "s-2"
  },
  {
    "long_name": "Canopy Water Storage",
    "sectors": [
      "water_global"
    ],
    "specifier": "canopystor",
    "units": "kg m-2",
    "valid_max": 10000.0,
    "valid_min": 0.0
  },
  {
    "long_name": "Catch of Large Consumers >90cm and <100kg",
    "sectors": [
      "marine-fishery_global"
    ],
    "specifier": "clarge",
    "units": "g m-2"
  },
  {
    "long_name": "Carbon Mass in Leaves",
    "sectors": [
      "biomes",
      "forestry"
    ],
    "specifier": "cleaf",
    "units": "kg m-2"
  },
  {
    "sectors": [
      "forestry",
      "biomes",
      "permafrost"
    ],
    "specifier": "clitter",
    "units": "kg m-2"
  },
  {
    "long_name": "Catch of Medium Consumers >30cm and <90cm",
    "sectors": [
      "marine-fishery_global"
    ],
    "specifier": "cmed",
    "units": "g m-2"
  },
  {
    "long_name": "Carbon Mass in Roots",
    "sectors": [
      "biomes",
      "forestry"
    ],
    "specifier": "croot",
    "units": "kg m-2"
  },
  {
    "long_name": "Catch of Small Consumers <30cm",
    "sectors": [
      "marine-fishery_global"
    ],
    "specifier": "csmall",
    "units": "g m-2"
  },
  {
    "dimensions": [
      "time",
      "depth",
      "lat",
      "lon"
    ],
    "long_name": "Carbon Mass in Soil Pool",
    "sectors": [
      "biomes",
      "forestry",
      "permafrost"
    ],
    "specifier": "csoil",
    "units": "kg m-2"
  },
  {
    "long_name": "Carbon Mass in Vegetation",
    "sectors": [
      "biomes",
      "forestry",
      "permafrost"
    ],
    "specifier": "cveg",
    "units": "kg m-2"
  },
  {
    "long_name": "Carbon Mass in Above Ground Vegetation Biomass",
    "sectors": [
      "biomes",
      "forestry",
      "permafrost"
    ],
    "specifier": "cvegag",
    "units": "kg m-2"
  },
  {
    "long_name": "Carbon Mass in Below Ground Vegetation Biomass",
    "sectors": [
      "biomes",
      "forestry",
      "permafrost"
    ],
    "specifier": "cvegbg",
    "units": "kg m-2"
  },
  {
    "long_name": "Carbon Mass in Wood",
    "sectors": [
      "biomes",
      "forestry"
    ],
    "specifier": "cwood",
    "units": "kg m-2"
  },
  {
    "long_name": "Mean DBH",
    "sectors": [
      "forestry"
    ],
    "specifier": "dbh",
    "units": "cm"
  },
  {
    "long_name": "Mean DBH of 100 Highest Trees",
    "sectors": [
      "forestry"
    ],
    "specifier": "dbhdomhei",
    "units": "cm"
  },
  {
    "long_name": "Discharge",
    "sectors": [
      "biomes",
      "water_global",
      "water_regional"
    ],
    "specifier": "dis",
    "units": "m3 s-1",
    "valid_max": 700000.0,
    "valid_min": 0.0
  },
  {
    "long_name": "Volume of Disturbance Damage",
    "sectors": [
      "forestry"
    ],
    "specifier": "dist",
    "units": "m3 ha-1"
  },
  {
    "long_name": "Stand Density",
    "sectors": [
      "forestry"
    ],
    "specifier": "density",
    "units": "m2 ha-1"
  },
  {
    "long_name": "Dominant Height",
    "sectors": [
      "forestry"
    ],
    "specifier": "domhei",
    "units": "m2 ha-1"
  },
  {
    "sectors": [
      "biomes",
      "permafrost"
    ],
    "specifier": "ecoatmflux",
    "units": "kg m-2 s-1"
  },
  {
    "long_name": "Summed Probability of Endemic Amphibian Species",
    "sectors": [
      "biodiversity"
    ],
    "specifier": "endamphibiansumprob",
    "units": "Summed probability of occurrence per cell"
  },
  {
    "long_name": "Summed Probability of Endemic Terrestrial Bird Species",
    "sectors": [
      "biodiversity"
    ],
    "specifier": "endbirdsumprob",
    "units": "Summed probability of occurrence per cell"
  },
  {
    "long_name": "Summed Probability of Endemic Terrestrial Mammal Species",
    "sectors": [
      "biodiversity"
    ],
    "specifier": "endmammalsumprob",
    "units": "Summed probability of occurrence per cell"
  },
  {
    "long_name": "Water Evaporation from Soil",
    "sectors": [
      "biomes",
      "forestry",
      "water_global"
    ],
    "specifier": "esoil",
    "units": "kg m-2 s-1"
  },
  {
    "long_name": "Evapotranspiration",
    "sectors": [
      "biomes",
      "forestry",
      "water_global",
      "water_regional"
    ],
    "specifier": "evap",
    "units": "kg m-2 s-1",
    "valid_max": 0.004,
    "valid_min": 0.0
  },
  {
    "long_name": "Fraction of Absorbed Photosynthetically Active Radiation",
    "sectors": [
      "biomes",
      "forestry",
      "permafrost"
    ],
    "specifier": "fapar",
    "units": "%"
  },
  {
    "sectors": [
      "biomes"
    ],
    "specifier": "firefrac"
  },
  {
    "long_name": "Carbon Mass Flux into atmosphere due to total Carbon emissions from Fire",
    "sectors": [
      "biomes",
      "permafrost"
    ],
    "specifier": "fireint",
    "units": "kg m-2 s-1"
  },
  {
    "long_name": "Carbon Mass Flux out of Atmosphere due to Gross Primary Production on Land",
    "sectors": [
      "biomes",
      "forestry",
      "permafrost"
    ],
    "specifier": "gpp",
    "units": "kg m-2 s-1"
  },
  {
    "long_name": "Groundwater Storage",
    "sectors": [
      "water_global"
    ],
    "specifier": "groundwstor",
    "units": "kg m-2",
    "valid_max": 20000.0,
    "valid_min": -200000.0
  },
  {
    "long_name": "Accumulated Growing Season Precipitation",
    "sectors": [
      "agriculture"
    ],
    "specifier": "gsprcp",
    "units": "mm ha-1 yr-1"
  },
  {
    "long_name": "Growing Season Incoming Solar Shortwave Radiation",
    "sectors": [
      "agriculture"
    ],
    "specifier": "gsrsds",
    "units": "W m-2 yr-1"
  },
  {
    "dimensions": [
      "time",
      "dbhclass",
      "lat",
      "lon"
    ],
    "long_name": "Harvest by DBH-Class",
    "sectors": [
      "forestry"
    ],
    "specifier": "harv",
    "units": "m3 ha-1"
  },
  {
    "dimensions": [
      "time",
      "dbhclass",
      "lat",
      "lon"
    ],
    "long_name": "Removed Stem Numbers by DBH-Class by Management",
    "sectors": [
      "forestry"
    ],
    "specifier": "harvstemno",
    "units": "ha-1"
  },
  {
    "long_name": "Stand Height",
    "sectors": [
      "forestry"
    ],
    "specifier": "hei",
    "units": "m ha-1"
  },
  {
    "long_name": "Lake Ice Cover",
    "sectors": [
      "lakes_global",
      "lakes_local"
    ],
    "specifier": "ice",
    "units": "1"
  },
  {
    "long_name": "Ice Thickness",
    "sectors": [
      "lakes_global",
      "lakes_local"
    ],
    "specifier": "icethick",
    "units": "m"
  },
  {
    "long_name": "Ice Temperature at Upper Surface",
    "sectors": [
      "lakes_global",
      "lakes_local"
    ],
    "specifier": "icetemp",
    "units": "K"
  },
  {
    "products": [
      "SecondaryOutputData"
    ],
    "sectors": [
      "lakes_global",
      "lakes_local"
    ],
    "specifier": "icedur"
  },
  {
    "products": [
      "SecondaryOutputData"
    ],
    "sectors": [
      "lakes_global",
      "lakes_local"
    ],
    "specifier": "iceend"
  },
  {
    "products": [
      "SecondaryOutputData"
    ],
    "sectors": [
      "lakes_global",
      "lakes_local"
    ],
    "specifier": "icestart"
  },
  {
    "long_name": "Nitrogen Application Rate",
    "sectors": [
      "agriculture"
    ],
    "specifier": "initr",
    "units": "kg ha-1 per growing season"
  },
  {
    "long_name": "Evaporation from Canopy (interception)",
    "sectors": [
      "biomes",
      "forestry"
    ],
    "specifier": "intercep",
    "units": "kg m-2 s-1"
  },
  {
    "long_name": "Leaf Area Index",
    "sectors": [
      "biomes",
      "forestry",
      "permafrost",
      "water_global"
    ],
    "specifier": "lai",
    "units": "1",
    "valid_max": 10.0,
    "valid_min": 0.0
  },
  {
    "long_name": "Downward Heat Flux at Lake-Atmosphere Interface",
    "sectors": [
      "lakes_global",
      "lakes_local"
    ],
    "specifier": "lakeheatf",
    "units": "W m-2"
  },
  {
    "long_name": "Turbulent Diffusivity of Heat",
    "sectors": [
      "lakes_global",
      "lakes_local"
    ],
    "specifier": "turbdiffheat",
    "units": "m2 s-1"
  },
  {
    "long_name": "Latent Heat Flux at Lake-Atmosphere Interface",
    "sectors": [
      "lakes_global",
      "lakes_local"
    ],
    "specifier": "latentheatf",
    "units": "W m-2"
  },
  {
    "long_name": "Lake Water Storage",
    "sectors": [
      "water_global"
    ],
    "specifier": "lakestor",
    "units": "kg m-2",
    "valid_max": 200000.0,
    "valid_min": -200000.0
  },
  {
    "long_name": "Lake Layer Ice Mass Fraction",
    "sectors": [
      "lakes_global",
      "lakes_local"
    ],
    "specifier": "lakeicefrac",
    "units": "1"
  },
  {
    "long_name": "Nitrogen Leached",
    "sectors": [
      "agriculture"
    ],
    "specifier": "leach",
    "units": ""
  },
  {
    "long_name": "Upward Long-Wave Radiation Flux at Lake-Atmosphere Interface",
    "sectors": [
      "lakes_global",
      "lakes_local"
    ],
    "specifier": "lwup",
    "units": "W m-2"
  },
  {
    "long_name": "Mean Annual Increment",
    "sectors": [
      "forestry"
    ],
    "specifier": "mai",
    "units": "m3 ha-1"
  },
  {
    "long_name": "Terrestrial Mammal Species Probability of Occurrence",
    "sectors": [
      "biodiversity"
    ],
    "specifier": "mammalprob",
    "units": "Probability of occurrence per cell"
  },
  {
    "long_name": "Terrestrial Mammal Species Richness",
    "sectors": [
      "biodiversity"
    ],
    "specifier": "mammalsr",
    "units": "Estimated number of species (species richness) per cell"
  },
  {
    "long_name": "Terrestrial Mammal Summed Probability of Occurrence",
    "sectors": [
      "biodiversity"
    ],
    "specifier": "mammalsumprob",
    "units": "Summed probability of occurrence per cell"
  },
  {
    "long_name": "Maturity Date",
    "sectors": [
      "agriculture"
    ],
    "specifier": "matyday",
    "units": "day of year of maturity"
  },
  {
    "long_name": "Year of Maturity",
    "sectors": [
      "agriculture"
    ],
    "specifier": "matyyear",
    "units": "year of maturity"
  },
  {
    "sectors": [
      "water_global"
    ],
    "specifier": "maxdis"
  },
  {
    "sectors": [
      "water_global"
    ],
    "specifier": "mindis"
  },
  {
    "long_name": "Momentum Flux at Lake-Atmosphere Interface",
    "sectors": [
      "lakes_global",
      "lakes_local"
    ],
    "specifier": "momf",
    "units": "kg m-1 s-2"
  },
  {
    "long_name": "Volume of Dead Trees",
    "sectors": [
      "forestry"
    ],
    "specifier": "mort",
    "units": "m3 ha-1"
  },
  {
    "dimensions": [
      "time",
      "dbhclass",
      "lat",
      "lon"
    ],
    "long_name": "Removed Stem Numbers by DBH-Class by Natural Mortality",
    "sectors": [
      "forestry"
    ],
    "specifier": "mortstemno",
    "units": "ha-1"
  },
  {
    "long_name": "Net Ecosystem Exchange",
    "sectors": [
      "forestry"
    ],
    "specifier": "nee",
    "units": "kg m-2 s-1"
  },
  {
    "long_name": "Nitrogen of Annual Litter",
    "sectors": [
      "forestry"
    ],
    "specifier": "nlit",
    "units": "g m-2 a-1"
  },
  {
    "long_name": "Carbon Mass Flux out of Atmosphere due to Net Primary Production on Land",
    "sectors": [
      "biomes",
      "forestry",
      "permafrost"
    ],
    "specifier": "npp",
    "units": "kg m-2 s-1"
  },
  {
    "long_name": "Net Primary Production allocated to leaf biomass",
    "sectors": [
      "biomes",
      "forestry",
      "permafrost"
    ],
    "specifier": "nppleaf",
    "units": "kg m-2 s-1"
  },
  {
    "long_name": "Net Primary Production allocated to fine root biomass",
    "sectors": [
      "biomes",
      "forestry",
      "permafrost"
    ],
    "specifier": "npproot",
    "units": "kg m-2 s-1"
  },
  {
    "sectors": [
      "biomes",
      "permafrost"
    ],
    "specifier": "nppagwood",
    "units": "kg m-2 s-1"
  },
  {
    "sectors": [
      "biomes",
      "permafrost"
    ],
    "specifier": "nppbgwood",
    "units": "kg m-2 s-1"
  },
  {
    "sectors": [
      "biomes",
      "permafrost"
    ],
    "specifier": "npplandleaf",
    "units": "kg m-2 s-1"
  },
  {
    "sectors": [
      "biomes",
      "permafrost"
    ],
    "specifier": "npplandroot",
    "units": "kg m-2 s-1"
  },
  {
    "sectors": [
      "biomes",
      "permafrost"
    ],
    "specifier": "nppabovegroundwood",
    "units": "kg m-2 s-1"
  },
  {
    "sectors": [
      "biomes",
      "permafrost"
    ],
    "specifier": "nppbelowgroundwood",
    "units": "kg m-2 s-1"
  },
  {
    "long_name": "Nitrogen in Soil",
    "sectors": [
      "forestry"
    ],
    "specifier": "nsoil",
    "units": "g m-2 a-1"
  },
  {
    "long_name": "Potential Domestic Water Consumption",
    "sectors": [
      "water_global"
    ],
    "specifier": "pdomuse",
    "units": "kg m-2 s-1",
    "valid_max": 0.002,
    "valid_min": 0.0
  },
  {
    "long_name": "Plant Functional Type Grid Fraction",
    "sectors": [
      "biomes",
      "permafrost"
    ],
    "specifier": "pft",
    "units": "%"
  },
  {
    "sectors": [
      "biomes"
    ],
    "specifier": "pft2storeys"
  },
  {
    "sectors": [
      "water_global"
    ],
    "specifier": "pidmeluse"
  },
  {
    "sectors": [
      "water_global"
    ],
    "specifier": "pidmelww"
  },
  {
    "long_name": "Potential Irrigation Water Consumption",
    "sectors": [
      "water_global"
    ],
    "specifier": "pirruse",
    "units": "kg m-2 s-1",
    "valid_max": 0.002,
    "valid_min": 0.0
  },
  {
    "long_name": "Potential Irrigation Green Water Consumption on Irrigated Cropland",
    "sectors": [
      "water_global"
    ],
    "specifier": "pirrusegreen",
    "units": "kg m-2 s-1",
    "valid_max": 0.002,
    "valid_min": 0.0
  },
  {
    "long_name": "Potential Irrigation Water Withdrawal (assuming unlimited water supply)",
    "sectors": [
      "agriculture",
      "water_global"
    ],
    "specifier": "pirrww",
    "units": "kg m-2 s-1",
    "valid_max": 0.002,
    "valid_min": 0.0
  },
  {
    "long_name": "Actual Planting Date",
    "sectors": [
      "agriculture"
    ],
    "specifier": "plantday",
    "units": "day of year"
  },
  {
    "long_name": "Actual Planting Year",
    "sectors": [
      "agriculture"
    ],
    "specifier": "plantyear",
    "units": "year of planting"
  },
  {
    "long_name": "Potential manufacturing Water Consumption",
    "sectors": [
      "water_global"
    ],
    "specifier": "pmanuse",
    "units": "kg m-2 s-1",
    "valid_max": 0.002,
    "valid_min": 0.0
  },
  {
    "long_name": "Potential Evapotranspiration",
    "sectors": [
      "biomes",
      "water_global",
      "water_regional"
    ],
    "specifier": "potevap",
    "units": "kg m-2 s-1",
    "valid_max": 0.004,
    "valid_min": 0.0
  },
  {
    "long_name": "Total Potential Water Consumption (all sectors)",
    "sectors": [
      "water_global"
    ],
    "specifier": "ptotuse",
    "units": "kg m-2 s-1",
    "valid_max": 0.002,
    "valid_min": 0.0
  },
  {
    "long_name": "Total Potential Water Withdrawal (all sectors)",
    "sectors": [
      "water_global"
    ],
    "specifier": "ptotww",
    "units": "kg m-2 s-1",
    "valid_max": 0.002,
    "valid_min": 0.0
  },
  {
    "sectors": [
      "water_regional"
    ],
    "specifier": "qbaseflow"
  },
  {
    "long_name": "Groundwater Runoff",
    "sectors": [
      "water_global",
      "water_regional"
    ],
    "specifier": "qg",
    "units": "kg m-2 s-1",
    "valid_max": 0.002,
    "valid_min": 0.0
  },
  {
    "sectors": [
      "water_global"
    ],
    "specifier": "qint"
  },
  {
    "long_name": "Groundwater Recharge",
    "sectors": [
      "water_regional",
      "water_global"
    ],
    "specifier": "qr",
    "units": "kg m-2 s-1",
    "valid_max": 0.002,
    "valid_min": 0.0
  },
  {
    "sectors": [
      "water_regional"
    ],
    "specifier": "qrecharge"
  },
  {
    "long_name": "Surface Runoff",
    "sectors": [
      "biomes",
      "permafrost",
      "water_global",
      "water_regional"
    ],
    "specifier": "qs",
    "units": "kg m-2 s-1",
    "valid_max": 0.004,
    "valid_min": 0.0
  },
  {
    "long_name": "Subsurface Runoff",
    "sectors": [
      "biomes",
      "water_global"
    ],
    "specifier": "qsb",
    "units": "kg m-2 s-1",
    "valid_max": 0.002,
    "valid_min": 0.0
  },
  {
    "long_name": "Total Runoff",
    "sectors": [
      "biomes",
      "permafrost",
      "water_global",
      "water_regional"
    ],
    "specifier": "qtot",
    "units": "kg m-2 s-1",
    "valid_max": 0.015,
    "valid_min": 0.0
  },
  {
    "long_name": "Carbon Mass Flux into Atmosphere due to Autotrophic (plant) Respiration on Land",
    "sectors": [
      "biomes",
      "forestry",
      "permafrost"
    ],
    "specifier": "ra",
    "units": "kg m-2 s-1"
  },
  {
    "sectors": [
      "water_global",
      "water_regional",
      "biomes"
    ],
    "specifier": "rainf"
  },
  {
    "long_name": "Reservoir Water Storage",
    "sectors": [
      "water_global"
    ],
    "specifier": "reservoirstor",
    "units": "kg m-2",
    "valid_max": 150000.0,
    "valid_min": 0.0
  },
  {
    "long_name": "Carbon Mass Flux into Atmosphere due to Heterotrophic Respiration on Land",
    "sectors": [
      "biomes",
      "forestry",
      "permafrost"
    ],
    "specifier": "rh",
    "units": "kg m-2 s-1"
  },
  {
    "long_name": "River Water Storage",
    "sectors": [
      "water_global"
    ],
    "specifier": "riverstor",
    "units": "kg m-2",
    "valid_max": 50000.0,
    "valid_min": 0.0
  },
  {
    "dimensions": [
      "time",
      "depth",
      "lat",
      "lon"
    ],
    "long_name": "Soil Moisture Content at Root Zone",
    "sectors": [
      "water_global",
      "water_regional"
    ],
    "specifier": "rootmoist",
    "units": "kg m-2",
    "valid_max": 10000.0,
    "valid_min": 0.0
  },
  {
    "long_name": "Root autotrophic respiration",
    "sectors": [
      "biomes",
      "forestry"
    ],
    "specifier": "rr",
    "units": "kg m-2 s-1"
  },
  {
    "long_name": "Soil Carbon Emissions ",
    "sectors": [
      "agriculture"
    ],
    "specifier": "sco2",
    "units": "kg C ha-1"
  },
  {
    "long_name": "Sediment Upward Heat Flux at Lake-Sediment Interface",
    "sectors": [
      "lakes_global",
      "lakes_local"
    ],
    "specifier": "sedheatf",
    "units": "W m-2"
  },
  {
    "long_name": "Chlorophyll Concentration",
    "sectors": [
      "lakes_global",
      "lakes_local"
    ],
    "specifier": "chl",
    "units": "g-3 m-3"
  },
  {
    "long_name": "Phytoplankton Functional Group Biomass",
    "sectors": [
      "lakes_global",
      "lakes_local"
    ],
    "specifier": "phytobio",
    "units": "mole m-3 as carbon"
  },
  {
    "long_name": "Zooplankton Biomass",
    "sectors": [
      "lakes_global",
      "lakes_local"
    ],
    "specifier": "zoobio",
    "units": "mole m-3 as carbon"
  },
  {
    "long_name": "Total Phosphorus",
    "sectors": [
      "lakes_global",
      "lakes_local"
    ],
    "specifier": "tp",
    "units": "mole m-3"
  },
  {
    "long_name": "Particulate Phosphorus",
    "sectors": [
      "lakes_global",
      "lakes_local"
    ],
    "specifier": "pp",
    "units": "mole m-3"
  },
  {
    "long_name": "Total Dissolved Phosphorus",
    "sectors": [
      "lakes_global",
      "lakes_local"
    ],
    "specifier": "tpd",
    "units": "mole m-3"
  },
  {
    "long_name": "Total Nitrogen",
    "sectors": [
      "lakes_global",
      "lakes_local"
    ],
    "specifier": "tn",
    "units": "mole m-3"
  },
  {
    "long_name": "Particulate Nitrogen",
    "sectors": [
      "lakes_global",
      "lakes_local"
    ],
    "specifier": "pn",
    "units": "mole m-3"
  },
  {
    "long_name": "Total Dissolved Nitrogen",
    "sectors": [
      "lakes_global",
      "lakes_local"
    ],
    "specifier": "tdn",
    "units": "mole m-3"
  },
  {
    "long_name": "Dissolved Oxygen",
    "sectors": [
      "lakes_global",
      "lakes_local"
    ],
    "specifier": "do",
    "units": "mole m-3"
  },
  {
    "long_name": "Dissolved Organic Carbon",
    "sectors": [
      "lakes_global",
      "lakes_local"
    ],
    "specifier": "doc",
    "units": "mole m-3"
  },
  {
    "long_name": "Dissolved Silica",
    "sectors": [
      "lakes_global",
      "lakes_local"
    ],
    "specifier": "si",
    "units": "mole m-3"
  },
  {
    "long_name": "Buoyancy Frequency",
    "sectors": [
      "lakes_global",
      "lakes_local"
    ],
    "specifier": "buoyancyfrequency",
    "units": "s-2"
  },
  {
    "long_name": "Snow depth",
    "sectors": [
      "biomes",
      "permafrost",
      "water_global"
    ],
    "specifier": "snd",
    "units": "m",
    "valid_max": 1000.0,
    "valid_min": 0.0
  },
  {
    "long_name": "Sensible Heat Flux at Lake-Atmosphere Interface",
    "sectors": [
      "lakes_global",
      "lakes_local"
    ],
    "specifier": "sensheatf",
    "units": "W m-2"
  },
  {
    "long_name": "Nitrous Oxide Emissions",
    "sectors": [
      "agriculture"
    ],
    "specifier": "sn2o",
    "units": "kg N2O-N ha-1"
  },
  {
    "sectors": [
      "water_global",
      "water_regional"
    ],
    "specifier": "snowf"
  },
  {
    "long_name": "Snow Temperature at Upper Surface",
    "sectors": [
      "lakes_global",
      "lakes_local"
    ],
    "specifier": "snowtemp",
    "units": "K"
  },
  {
    "long_name": "Snow Thickness",
    "sectors": [
      "lakes_global",
      "lakes_local"
    ],
    "specifier": "snowthick",
    "units": "m"
  },
  {
    "dimensions": [
      "time",
      "depth",
      "lat",
      "lon"
    ],
    "long_name": "Total Soil Moisture Content",
    "sectors": [
      "biomes",
      "forestry",
      "permafrost",
      "water_global",
      "water_regional"
    ],
    "specifier": "soilmoist",
    "units": "kg m-2",
    "valid_max": 10000.0,
    "valid_min": 0.0
  },
  {
    "dimensions": [
      "time",
      "depth",
      "lat",
      "lon"
    ],
    "long_name": "Frozen Soil Moisture Content",
    "sectors": [
      "permafrost",
      "water_global",
      "biomes"
    ],
    "specifier": "soilmoistfroz",
    "units": "kg m-2",
    "valid_max": 10000.0,
    "valid_min": 0.0
  },
  {
    "long_name": "Species Composition",
    "sectors": [
      "forestry"
    ],
    "specifier": "species",
    "units": "%"
  },
  {
    "dimensions": [
      "time",
      "dbhclass",
      "lat",
      "lon"
    ],
    "long_name": "Remaining Stem Number after Disturbance and Management by DBH-Class",
    "sectors": [
      "forestry"
    ],
    "specifier": "stemno",
    "units": "ha-1"
  },
  {
    "long_name": "Thermal Stratification",
    "sectors": [
      "lakes_global",
      "lakes_local"
    ],
    "specifier": "strat",
    "units": "1"
  },
  {
    "sectors": [
      "biomes"
    ],
    "specifier": "somcfire"
  },
  {
    "products": [
      "SecondaryOutputData"
    ],
    "sectors": [
      "lakes_global",
      "lakes_local"
    ],
    "specifier": "stratdur"
  },
  {
    "products": [
      "SecondaryOutputData"
    ],
    "sectors": [
      "lakes_global",
      "lakes_local"
    ],
    "specifier": "stratend"
  },
  {
    "products": [
      "SecondaryOutputData"
    ],
    "sectors": [
      "lakes_global",
      "lakes_local"
    ],
    "specifier": "stratstart"
  },
  {
    "long_name": "Growing Season Temperature Sum",
    "sectors": [
      "agriculture"
    ],
    "specifier": "sumt",
    "units": "deg c-days yr-1"
  },
  {
    "long_name": "Temperature of Lake Surface Water",
    "sectors": [
      "lakes_global",
      "lakes_local"
    ],
    "specifier": "surftemp",
    "units": "K"
  },
  {
    "long_name": "Snow Water Equivalent",
    "sectors": [
      "biomes",
      "permafrost",
      "water_global",
      "water_regional"
    ],
    "specifier": "swe",
    "units": "kg m-2",
    "valid_max": 200000.0,
    "valid_min": 0.0
  },
  {
    "long_name": "Upward Short-Wave Radiation Flux at Lake-Atmosphere Interface",
    "sectors": [
      "lakes_global",
      "lakes_local"
    ],
    "specifier": "swup",
    "units": "W m-2"
  },
  {
    "long_name": "Total Catch (all commercial functional groups / size classes)",
    "sectors": [
      "marine-fishery_global",
      "marine-fishery_regional"
    ],
    "specifier": "tc",
    "units": "g m-2"
  },
  {
    "long_name": "Total Catch of Consumers >10cm",
    "sectors": [
      "marine-fishery_global",
      "marine-fishery_regional"
    ],
    "specifier": "tc10cm",
    "units": "g m-2"
  },
  {
    "long_name": "Total Catch of Consumers >30cm",
    "sectors": [
      "marine-fishery_global",
      "marine-fishery_regional"
    ],
    "specifier": "tc30cm",
    "units": "g m-2"
  },
  {
    "long_name": "Total Consumer Biomass Density ",
    "sectors": [
      "marine-fishery_global",
      "marine-fishery_regional"
    ],
    "specifier": "tcb",
    "units": "g C m-2"
  },
  {
    "long_name": "Annual Maximum Thaw Depth",
    "sectors": [
      "permafrost",
      "water_global",
      "biomes"
    ],
    "specifier": "thawdepth",
    "units": "m",
    "valid_max": 100.0,
    "valid_min": 0.0
  },
  {
    "long_name": "Depth of Thermocline",
    "sectors": [
      "lakes_global",
      "lakes_local"
    ],
    "specifier": "thermodepth",
    "units": "m"
  },
  {
    "long_name": "Summed Probability of Threatened Amphibian Species",
    "sectors": [
      "biodiversity"
    ],
    "specifier": "thramphibiansumprob",
    "units": "Summed probability of occurrence per cell"
  },
  {
    "long_name": "Summed Probability of Threatened Terrestrial Bird Species",
    "sectors": [
      "biodiversity"
    ],
    "specifier": "thrbirdsumprob",
    "units": "Summed probability of occurrence per cell"
  },
  {
    "long_name": "Summed Probability of Threatened Terrestrial Mammal Species",
    "sectors": [
      "biodiversity"
    ],
    "specifier": "thrmammalsumprob",
    "units": "Summed probability of occurrence per cell"
  },
  {
    "long_name": "Total Landings (all commercial functional groups / size classes)",
    "sectors": [
      "marine-fishery_regional"
    ],
    "specifier": "tla",
    "units": "g m-2"
  },
  {
    "long_name": "Transpiration",
    "sectors": [
      "biomes",
      "forestry",
      "water_global"
    ],
    "specifier": "trans",
    "units": "kg m-2 s-1"
  },
  {
    "sectors": [
      "water_global"
    ],
    "specifier": "transp"
  },
  {
    "long_name": "Total System Biomass Density ",
    "sectors": [
      "marine-fishery_global",
      "marine-fishery_regional"
    ],
    "specifier": "tsb",
    "units": "g C m-2"
  },
  {
    "dimensions": [
      "time",
      "depth",
      "lat",
      "lon"
    ],
    "long_name": "Temperature of Soil",
    "sectors": [
      "biomes",
      "forestry",
      "permafrost",
      "water_global"
    ],
    "specifier": "tsl",
    "units": "K",
    "valid_max": 320.0,
    "valid_min": 250.0
  },
  {
    "long_name": "Total Water Storage",
    "sectors": [
      "water_global"
    ],
    "specifier": "tws",
    "units": "kg m-2",
    "valid_max": 200000.0,
    "valid_min": -200000.0
  },
  {
    "long_name": "Stand Volume",
    "sectors": [
      "forestry"
    ],
    "specifier": "vol",
    "units": "m3 ha-1"
  },
  {
    "long_name": "Temperature of Lake Water",
    "sectors": [
      "lakes_global",
      "lakes_local"
    ],
    "specifier": "watertemp",
    "units": "K"
  },
  {
    "long_name": "Mean Temperature of Lake Water",
    "products": [
      "SecondaryOutputData"
    ],
    "sectors": [
      "lakes_global",
      "lakes_local"
    ],
    "specifier": "meanwatertemp",
    "units": "K"
  },
  {
    "long_name": "Light Extinction Coefficient",
    "sectors": [
      "lakes_global"
    ],
    "specifier": "extcoeff",
    "units": "m-1"
  },
  {
    "long_name": "Wetland Water Storage",
    "sectors": [
      "water_global"
    ],
    "specifier": "wetlandstor",
    "units": "kg m-2",
    "valid_max": 10000.0,
    "valid_min": -10000.0
  },
  {
    "long_name": "Crop Yields",
    "sectors": [
      "agriculture"
    ],
    "specifier": "yield",
    "units": "t ha-1 (dry matter per growing season)"
  },
  {
    "long_name": "Temperature-related Deaths",
    "sectors": [
      "waterborne_diseases"
    ],
    "specifier": "excess-temp-mortality",
    "units": "Number of deaths"
  },
  {
    "long_name": "Temperature-related Incidence",
    "sectors": [
      "waterborne_diseases"
    ],
    "specifier": "excess-temp-incidence",
    "units": "Number of new cases"
  },
  {
    "long_name": "Temperature-related Prevalence",
    "sectors": [
      "waterborne_diseases"
    ],
    "specifier": "excess-temp-prevalence",
    "units": "Number of cases"
  },
  {
    "long_name": "Rainfall-related Deaths",
    "sectors": [
      "waterborne_diseases"
    ],
    "specifier": "excess-rain-mortality",
    "units": "Number of deaths"
  },
  {
    "long_name": "Rainfall-related Incidence",
    "sectors": [
      "waterborne_diseases"
    ],
    "specifier": "excess-rain-incidence",
    "units": "Number of new cases"
  },
  {
    "long_name": "Rainfall-related Prevalence",
    "sectors": [
      "waterborne_diseases"
    ],
    "specifier": "excess-rain-prevalence",
    "units": "Number of cases"
  },
  {
    "long_name": "Land area fraction exposed to river flood",
    "products": [
      "DerivedOutputData"
    ],
    "specifier": "ler",
    "standard_name": "land_area_fraction_exposed_to_river_flood",
    "units": "1"
  },
  {
    "long_name": "Land area fraction exposed to tropical cyclone",
    "products": [
      "DerivedOutputData"
    ],
    "specifier": "let",
    "standard_name": "land_area_fraction_exposed_to_tropical_cyclone",
    "units": "1"
  },
  {
    "long_name": "Land area fraction exposed to drought",
    "products": [
      "DerivedOutputData"
    ],
    "specifier": "led",
    "standard_name": "land_area_fraction_exposed_to_drought",
    "units": "1"
  },
  {
    "long_name": "Land area fraction exposed to heatwave",
    "products": [
      "DerivedOutputData"
    ],
    "specifier": "leh",
    "standard_name": "land_area_fraction_exposed_to_heatwave",
    "units": "1"
  },
  {
    "long_name": "Land area fraction exposed to crop failure",
    "products": [
      "DerivedOutputData"
    ],
    "specifier": "lec",
    "standard_name": "land_area_fraction_exposed_to_crop_failure",
    "units": "1"
  },
  {
    "long_name": "Land area fraction exposed to wildfire",
    "products": [
      "DerivedOutputData"
    ],
    "specifier": "lew",
    "standard_name": "land_area_fraction_exposed_to_wildfire",
    "units": "1"
  },
  {
    "long_name": "Population fraction exposed to river flood",
    "products": [
      "DerivedOutputData"
    ],
    "specifier": "per",
    "standard_name": "population_fraction_exposed_to_river_flood",
    "units": "1"
  },
  {
    "long_name": "Population fraction exposed to tropical cyclone",
    "products": [
      "DerivedOutputData"
    ],
    "specifier": "pet",
    "standard_name": "population_fraction_exposed_to_tropical_cyclone",
    "units": "1"
  },
  {
    "long_name": "Population fraction exposed to drought",
    "products": [
      "DerivedOutputData"
    ],
    "specifier": "ped",
    "standard_name": "population_fraction_exposed_to_drought",
    "units": "1"
  },
  {
    "long_name": "Population fraction exposed to heatwave",
    "products": [
      "DerivedOutputData"
    ],
    "specifier": "peh",
    "standard_name": "population_fraction_exposed_to_heatwave",
    "units": "1"
  },
  {
    "long_name": "Population fraction exposed to crop failure",
    "products": [
      "DerivedOutputData"
    ],
    "specifier": "pec",
    "standard_name": "population_fraction_exposed_to_crop_failure",
    "units": "1"
  },
  {
    "long_name": "Population fraction exposed to wildfire",
    "products": [
      "DerivedOutputData"
    ],
    "specifier": "pew",
    "standard_name": "population_fraction_exposed_to_wildfire",
    "units": "1"
  }
]
