{
  "commit": "25a27676e7f9b07ce161bfedc73fa810edf0f154",
  "path": "(?P<simulation_round>[A-Za-z0-9]+)/(?P<product>[A-Za-z]+)/(?P<category>[A-Za-z_]+)/(?P<subcategory>[a-z0-9-_]+)/(HYDE)$",
  "dataset": "^(?P<soc_dataset>[a-z0-9-]+)_(?P<soc_scenario>[a-z0-9]+)_(?P<resolution>[a-z0-9]+)_(?P<time_step>[a-z]+)",
  "file": "^(?P<soc_dataset>[a-z0-9-]+)_(?P<soc_scenario>[a-z0-9]+)_(?P<resolution>[a-z0-9]+)_(?P<time_step>[a-z]+)_(?P<start_year>\\d{4})_(?P<end_year>\\d{4})(.nc|.csv)",
  "suffix": [
    ".nc",
    ".csv"
  ],
  "specifiers": {},
  "specifiers_map": {
    "landuse_humaninfluences": "socioeconomic",
    "countrylevel": "national",
    "population": "pop"
  }
}