{
  "$schema": "http://json-schema.org/draft-07/schema#",
  "$id": "https://protocol.isimip.org/schema/schema/ISIMIP2b/OutputData/agriculture.json",
  "commit": "d47f0d48203882abbf679d89549ce16e13328840",
  "type": "object",
  "required": [
    "specifiers"
  ],
  "properties": {
    "specifiers": {
      "type": "object",
      "required": [
        "model",
        "climate_forcing",
        "bias_adjustment",
        "climate_scenario",
        "soc_scenario",
        "sens_scenario",
        "variable",
        "crop",
        "irrigation",
        "region",
        "time_step"
      ],
      "properties": {
        "model": {
          "type": "string",
          "enum": [
            "vip",
            "web-dhm-s",
            "atlantis_se-australia",
            "ewe_adriatic-sea",
            "ewe_cook-strait",
            "macroecological",
            "swbm",
            "epic-boku-pt",
            "air2water6par",
            "simstrat",
            "gepic-br",
            "gotilwaplus",
            "lpjml",
            "watergap3",
            "swim-nve",
            "pcr-globwb",
            "3pg",
            "landscape-dndc",
            "ewe_east-bass-strait",
            "swap",
            "ewe_nw-med-sea",
            "papsim-pm",
            "vic-iitgn",
            "3d-cmcc-fem",
            "gotm",
            "hbv-pik",
            "bioscen15-sdm-gbm",
            "swat-vub",
            "hbv-cma",
            "simstrat-uog",
            "vic",
            "vegas",
            "ewe_north-sea",
            "swim-cma",
            "epic-tamu",
            "clm45",
            "swat-tamu",
            "boats",
            "epic-boku-br",
            "osmose_humboldt-n",
            "vic-lake",
            "dbh",
            "gepic-pm",
            "mpi-hm",
            "albm",
            "swim-pik",
            "epic-boku-hg",
            "gepic",
            "ways",
            "dbpm",
            "orchidee",
            "ewe_baltic-sea",
            "wbd",
            "jules-es-55",
            "orchidee-dgvm",
            "ecoocean",
            "h08",
            "clm50",
            "apecosm",
            "hype",
            "dbem",
            "clm40",
            "visit",
            "mylake",
            "flake-igb",
            "watergap2",
            "ewe_med-glob",
            "bioscen15-mem-gam",
            "basfor",
            "swat-uottawa",
            "jules-b1",
            "orchidee-crop",
            "pdssat-pt",
            "pegasus",
            "glm",
            "cwatm",
            "air2water4par",
            "jules-w1",
            "swat-sggw",
            "swim-nve-v2",
            "lpj-guess",
            "hbv-iww",
            "forclim",
            "cgms-wofost",
            "prebas",
            "hymod-ufz",
            "vic-hhu",
            "clm-crop",
            "prysbi2",
            "vic-nve-v2",
            "vic-cma",
            "swat-ufz",
            "iapras-dss",
            "lake",
            "vic-nve",
            "epic-boku-pe",
            "3d-cmcc-cnr-bgc",
            "gepic-p",
            "papsim",
            "swat-cma",
            "gepic-pt",
            "bioscen15-mem-gbm",
            "caraib",
            "epic-iiasa",
            "pdssat",
            "hymod-jlu",
            "bioscen15-sdm-gam",
            "pepic",
            "ecomag",
            "epic-boku",
            "dlem",
            "hbv-jlu",
            "matsiro",
            "mhm",
            "swat-iitgn"
          ]
        },
        "climate_forcing": {
          "type": "string",
          "enum": [
            "miroc5",
            "hadgem2-es",
            "gfdl-esm2m",
            "ipsl-cm5a-lr"
          ]
        },
        "bias_adjustment": {
          "type": "string",
          "enum": [
            "ewembi",
            "nobc"
          ]
        },
        "climate_scenario": {
          "type": "string",
          "enum": [
            "2005co2",
            "picontrol",
            "rcp60",
            "2299rcp26",
            "rcp26",
            "rcp85",
            "rcp45",
            "historical"
          ]
        },
        "soc_scenario": {
          "type": "string",
          "enum": [
            "1860soc",
            "varsoc",
            "nosoc",
            "rcp26soc",
            "ssp5soc",
            "pressoc",
            "nat",
            "ssp2soc",
            "2005soc",
            "rcp60soc",
            "rcp85soc",
            "histsoc",
            "2100rcp26soc",
            "ssp3soc",
            "ssp4soc",
            "ssp1soc"
          ]
        },
        "sens_scenario": {
          "type": "string",
          "enum": [
            "default",
            "co2",
            "2005co2"
          ]
        },
        "variable": {
          "type": "string",
          "enum": [
            "leach",
            "plantday",
            "sco2",
            "gsprcp",
            "initr",
            "sn2o",
            "sumt",
            "yield",
            "matyday",
            "plantyear",
            "aet",
            "biom",
            "gsrsds",
            "matyyear",
            "anthday",
            "pirrww"
          ]
        },
        "crop": {
          "type": "string",
          "enum": [
            "cot",
            "sun",
            "pot",
            "whe",
            "pop",
            "mgr",
            "sgb",
            "nut",
            "mai",
            "rye",
            "ric",
            "cas",
            "mis",
            "sug",
            "ben",
            "euc",
            "sor",
            "ri1",
            "mil",
            "rap",
            "soy",
            "pea",
            "ri2",
            "bar"
          ]
        },
        "irrigation": {
          "type": "string",
          "enum": [
            "firr",
            "noirr"
          ]
        },
        "region": {
          "type": "string",
          "enum": [
            "global"
          ]
        },
        "time_step": {
          "type": "string",
          "enum": [
            "seasonal",
            "annual"
          ]
        },
        "start_year": {
          "type": "number"
        },
        "end_year": {
          "type": "number"
        }
      }
    }
  }
}