{
  "$schema": "http://json-schema.org/draft-07/schema#",
  "$id": "https://protocol.isimip.org/schema/schema/ISIMIP2b/OutputData/biodiversity.json",
  "commit": "0b4422f19e106facb519c4736872fd52f593ba5c",
  "type": "object",
  "required": [
    "specifiers"
  ],
  "properties": {
    "specifiers": {
      "type": "object",
      "required": [
        "model",
        "climate_forcing",
        "bias_adjustment",
        "climate_scenario",
        "soc_scenario",
        "sens_scenario",
        "variable",
        "region",
        "time_step"
      ],
      "properties": {
        "model": {
          "type": "string",
          "enum": [
            "vic-nve",
            "mhm",
            "dlem",
            "swbm",
            "ecoocean",
            "iapras-dss",
            "jules-es-55",
            "3pg",
            "pegasus",
            "landscape-dndc",
            "papsim",
            "clm-crop",
            "clm40",
            "gepic-pt",
            "jules-w1",
            "matsiro",
            "bioscen15-sdm-gbm",
            "gepic",
            "bioscen15-mem-gbm",
            "ewe_cook-strait",
            "epic-tamu",
            "ewe_nw-med-sea",
            "hbv-pik",
            "mpi-hm",
            "swim-nve",
            "flake-igb",
            "gotm",
            "vip",
            "watergap3",
            "dbh",
            "boats",
            "epic-boku-br",
            "clm45",
            "clm50",
            "swat-sggw",
            "swim-cma",
            "epic-boku-pe",
            "h08",
            "ewe_north-sea",
            "bioscen15-sdm-gam",
            "swat-iitgn",
            "gotilwaplus",
            "swat-cma",
            "epic-boku-hg",
            "osmose_humboldt-n",
            "swat-tamu",
            "simstrat",
            "pdssat-pt",
            "pdssat",
            "ways",
            "3d-cmcc-fem",
            "visit",
            "hbv-jlu",
            "orchidee-crop",
            "gepic-p",
            "hymod-ufz",
            "epic-boku-pt",
            "pcr-globwb",
            "forclim",
            "prysbi2",
            "albm",
            "apecosm",
            "hbv-iww",
            "lpjml",
            "web-dhm-s",
            "vic-hhu",
            "glm",
            "ewe_east-bass-strait",
            "dbem",
            "caraib",
            "bioscen15-mem-gam",
            "lpj-guess",
            "vic-cma",
            "swap",
            "epic-iiasa",
            "atlantis_se-australia",
            "ewe_med-glob",
            "lake",
            "hymod-jlu",
            "hype",
            "vic-iitgn",
            "3d-cmcc-cnr-bgc",
            "vegas",
            "watergap2",
            "basfor",
            "orchidee-dgvm",
            "simstrat-uog",
            "vic-lake",
            "air2water4par",
            "prebas",
            "jules-b1",
            "air2water6par",
            "gepic-pm",
            "ewe_baltic-sea",
            "vic",
            "wbd",
            "ecomag",
            "cgms-wofost",
            "ewe_adriatic-sea",
            "swat-ufz",
            "swat-vub",
            "gepic-br",
            "epic-boku",
            "cwatm",
            "dbpm",
            "pepic",
            "papsim-pm",
            "orchidee",
            "mylake",
            "swim-pik",
            "macroecological"
          ]
        },
        "climate_forcing": {
          "type": "string",
          "enum": [
            "miroc5",
            "ipsl-cm5a-lr",
            "gfdl-esm2m",
            "hadgem2-es"
          ]
        },
        "bias_adjustment": {
          "type": "string",
          "enum": [
            "nobc",
            "ewembi"
          ]
        },
        "climate_scenario": {
          "type": "string",
          "enum": [
            "rcp45",
            "2005co2",
            "rcp26",
            "rcp60",
            "historical",
            "picontrol",
            "rcp85"
          ]
        },
        "soc_scenario": {
          "type": "string",
          "enum": [
            "ssp3soc",
            "1860soc",
            "2005soc",
            "rcp26soc",
            "ssp2soc",
            "ssp4soc",
            "ssp1soc",
            "rcp60soc",
            "nat",
            "varsoc",
            "pressoc",
            "2100rcp26soc",
            "ssp5soc",
            "histsoc",
            "nosoc"
          ]
        },
        "sens_scenario": {
          "type": "string",
          "enum": [
            "co2",
            "default",
            "2005co2"
          ]
        },
        "variable": {
          "type": "string",
          "enum": [
            "endmammalsumprob",
            "mammalsumprob",
            "birdsr",
            "endbirdsumprob",
            "thrbirdsumprob",
            "birdprob",
            "amphibiansr",
            "lakeheatf",
            "thramphibiansumprob",
            "thrmammalsumprob",
            "mammalsr",
            "birdsumprob",
            "mammalprob",
            "endamphibiansumprob",
            "amphibiansumprob"
          ]
        },
        "region": {
          "type": "string",
          "enum": [
            "global"
          ]
        },
        "time_step": {
          "type": "string",
          "enum": [
            "30year-mean"
          ]
        },
        "start_year": {
          "type": "number"
        },
        "end_year": {
          "type": "number"
        }
      }
    }
  }
}