{
  "$schema": "http://json-schema.org/draft-07/schema#",
  "$id": "https://protocol.isimip.org/schema/schema/ISIMIP2b/OutputData/lakes_global.json",
  "commit": "fe4bfdd95fe53b93ed16f5921fd8def7cce04f09",
  "type": "object",
  "required": [
    "specifiers"
  ],
  "properties": {
    "specifiers": {
      "type": "object",
      "required": [
        "model",
        "climate_forcing",
        "bias_adjustment",
        "climate_scenario",
        "soc_scenario",
        "sens_scenario",
        "variable",
        "region",
        "time_step"
      ],
      "properties": {
        "model": {
          "type": "string"
        },
        "climate_forcing": {
          "type": "string",
          "enum": [
            "cesm1-bgc",
            "ipsl-cm5a-lr",
            "miroc5",
            "gfdl-esm2m",
            "hadgem2-es"
          ]
        },
        "bias_adjustment": {
          "type": "string",
          "enum": [
            "ewembi",
            "nobc"
          ]
        },
        "climate_scenario": {
          "type": "string",
          "enum": [
            "rcp60",
            "2005co2",
            "rcp26",
            "rcp45",
            "historical",
            "rcp85",
            "picontrol",
            "2299rcp26"
          ]
        },
        "soc_scenario": {
          "type": "string",
          "enum": [
            "1860soc",
            "rcp26socbeb",
            "nat",
            "2100rcp26soc",
            "nosoc",
            "rcp85sochwp",
            "rcp60sochwp",
            "rcp60socbeb",
            "rcp60socbe",
            "ssp2soc",
            "2005soc",
            "2005socsite",
            "ssp5soc",
            "rcp26sochwp",
            "rcp60socam",
            "rcp60soc",
            "rcp85soc",
            "ssp1soc",
            "rcp26soc",
            "rcp26soca",
            "rcp85soca",
            "varsoc",
            "ssp3soc",
            "histsoc",
            "pressoc",
            "rcp85socbeb",
            "rcp26socam",
            "rcp26socbe",
            "rcp60soca",
            "ssp4soc",
            "rcp85socbe",
            "rcp85socam"
          ]
        },
        "sens_scenario": {
          "type": "string",
          "enum": [
            "default",
            "co2",
            "2005co2"
          ]
        },
        "variable": {
          "type": "string",
          "enum": [
            "snowtemp",
            "sensheatf",
            "pn",
            "zoobio",
            "icetemp",
            "chl",
            "latentheatf",
            "tn",
            "si",
            "snowthick",
            "turbdiffheat",
            "icethick",
            "buoyancyfrequency",
            "sedheatf",
            "tpd",
            "strat",
            "swup",
            "pp",
            "lakeheatf",
            "phytobio",
            "extcoeff",
            "tdn",
            "tp",
            "momf",
            "bottemp",
            "lakeicefrac",
            "do",
            "albedo",
            "lwup",
            "watertemp",
            "thermodepth",
            "ice",
            "doc",
            "surftemp"
          ]
        },
        "region": {
          "type": "string",
          "enum": [
            "global"
          ]
        },
        "time_step": {
          "type": "string",
          "enum": [
            "monthly",
            "annual",
            "seasonal",
            "daily"
          ]
        },
        "start_year": {
          "type": "number"
        },
        "end_year": {
          "type": "number"
        }
      }
    }
  }
}