{
  "$schema": "http://json-schema.org/draft-07/schema#",
  "$id": "https://protocol.isimip.org/schema/schema/ISIMIP2b/OutputData/lakes_local.json",
  "commit": "aae3370c207b429c8d1c761c49e87d6e7b9754dc",
  "type": "object",
  "required": [
    "specifiers"
  ],
  "properties": {
    "specifiers": {
      "type": "object",
      "required": [
        "model",
        "climate_forcing",
        "bias_adjustment",
        "climate_scenario",
        "soc_scenario",
        "sens_scenario",
        "variable",
        "lake_site",
        "time_step"
      ],
      "properties": {
        "model": {
          "type": "string",
          "enum": [
            "hbv-jlu",
            "mpi-hm",
            "swat-ufz",
            "ewe_east-bass-strait",
            "epic-tamu",
            "swap",
            "clm40",
            "dbh",
            "3pg",
            "dbpm",
            "swat-sggw",
            "ways",
            "iapras-dss",
            "watergap2",
            "papsim",
            "landscape-dndc",
            "3d-cmcc-fem",
            "caraib",
            "mhm",
            "lpjml",
            "matsiro",
            "pegasus",
            "jules-w1",
            "dlem",
            "hbv-iww",
            "hbv-pik",
            "basfor",
            "swbm",
            "osmose_humboldt-n",
            "ecomag",
            "clm50",
            "orchidee-dgvm",
            "lpj-guess",
            "clm45",
            "macroecological",
            "hymod-ufz",
            "swat-iitgn",
            "albm",
            "hymod-jlu",
            "orchidee",
            "visit",
            "pdssat",
            "prebas",
            "pepic",
            "ewe_adriatic-sea",
            "vegas",
            "ewe_med-glob",
            "swim-cma",
            "bioscen15-mem-gam",
            "pcr-globwb",
            "vic-cma",
            "vic-hhu",
            "forclim",
            "h08",
            "vic-iitgn",
            "vip",
            "cwatm",
            "clm-crop",
            "watergap3",
            "gepic",
            "3d-cmcc-cnr-bgc",
            "ewe_north-sea",
            "bioscen15-sdm-gam",
            "simstrat-uog",
            "cgms-wofost",
            "gotilwaplus",
            "ewe_nw-med-sea",
            "bioscen15-sdm-gbm",
            "swat-tamu",
            "ewe_cook-strait",
            "prysbi2",
            "simstrat",
            "bioscen15-mem-gbm",
            "swim-pik",
            "dbem",
            "swat-vub",
            "apecosm",
            "vic",
            "ewe_baltic-sea",
            "jules-b1",
            "vic-lake",
            "orchidee-crop",
            "glm",
            "hype",
            "ecoocean",
            "epic-iiasa",
            "atlantis_se-australia",
            "gotm",
            "epic-boku",
            "swim-nve",
            "vic-nve",
            "lake",
            "swat-cma",
            "boats"
          ]
        },
        "climate_forcing": {
          "type": "string",
          "enum": [
            "miroc5",
            "hadgem2-es",
            "ipsl-cm5a-lr",
            "gfdl-esm2m"
          ]
        },
        "bias_adjustment": {
          "type": "string",
          "enum": [
            "nobc",
            "ewembi"
          ]
        },
        "climate_scenario": {
          "type": "string",
          "enum": [
            "rcp26",
            "historical",
            "rcp60",
            "rcp45",
            "rcp85",
            "2005co2",
            "picontrol"
          ]
        },
        "soc_scenario": {
          "type": "string",
          "enum": [
            "nat",
            "2005soc",
            "1860soc",
            "histsoc",
            "rcp26soc",
            "2100rcp26soc",
            "rcp60soc",
            "varsoc",
            "pressoc",
            "nosoc"
          ]
        },
        "sens_scenario": {
          "type": "string",
          "enum": [
            "default",
            "2005co2",
            "co2"
          ]
        },
        "variable": {
          "type": "string",
          "enum": [
            "snowtemp",
            "sensheatf",
            "surftemp",
            "icetemp",
            "snowthick",
            "thermodepth",
            "bottemp",
            "lwup",
            "sedheatf",
            "lakeicefrac",
            "strat",
            "momf",
            "lakeheatf",
            "latentheatf",
            "ice",
            "swup",
            "icethick",
            "albedo",
            "watertemp"
          ]
        },
        "lake_site": {
          "type": "string",
          "enum": [
            "tarawera",
            "falling-creek",
            "alqueva",
            "black-oak",
            "mt-bold",
            "sammamish",
            "trout-bog",
            "toolik",
            "burley-griffin",
            "crystal-lake",
            "kilpisjarvi",
            "kuivajarvi",
            "esthwaite-water",
            "neuchatel",
            "lower-zurich",
            "klicava",
            "ngoring ",
            "trout-lake",
            "nohipalo-mustjaerv",
            "washington",
            "kivu",
            "two-sisters",
            "paajarvi",
            "great",
            "tahoe",
            "rimov",
            "green",
            "fish",
            "eagle ",
            "monona",
            "stechlin",
            "rappbode",
            "kinneret",
            "delavan",
            "vendyurskoe",
            "laramie",
            "wingra",
            "big-muskellunge",
            "waahi",
            "bourget",
            "annie",
            "harp",
            "sparkling",
            "okauchee",
            "erken",
            "geneva",
            "windermere",
            "ekoln ",
            "langtjern",
            "rotorua",
            "dickie",
            "sunapee",
            "taupo",
            "vortsjaerv",
            "sau",
            "crystal-bog",
            "zlutice",
            "feeagh",
            "argyle",
            "annecy",
            "mozhaysk",
            "biel",
            "nohipalo-valgejaerv",
            "mueggelsee",
            "mendota"
          ]
        },
        "time_step": {
          "type": "string",
          "enum": [
            "daily",
            "monthly",
            "annual"
          ]
        },
        "start_year": {
          "type": "number"
        },
        "end_year": {
          "type": "number"
        }
      }
    }
  }
}