{
  "$schema": "http://json-schema.org/draft-07/schema#",
  "$id": "https://protocol.isimip.org/schema/schema/ISIMIP2b/OutputData/marine-fishery_global.json",
  "commit": "0d948fc405a24b13b708523ea3efe6ee05c6d27a",
  "type": "object",
  "required": [
    "specifiers"
  ],
  "properties": {
    "specifiers": {
      "type": "object",
      "required": [
        "model",
        "climate_forcing",
        "bias_adjustment",
        "climate_scenario",
        "variable",
        "region",
        "time_step"
      ],
      "properties": {
        "model": {
          "type": "string"
        },
        "climate_forcing": {
          "type": "string",
          "enum": [
            "hadgem2-es",
            "ipsl-cm5a-lr",
            "miroc5",
            "cesm1-bgc",
            "gfdl-esm2m"
          ]
        },
        "bias_adjustment": {
          "type": "string",
          "enum": [
            "nobc",
            "ewembi"
          ]
        },
        "climate_scenario": {
          "type": "string",
          "enum": [
            "rcp60",
            "rcp85",
            "2005co2",
            "rcp26",
            "historical",
            "picontrol",
            "2299rcp26",
            "rcp45"
          ]
        },
        "variable": {
          "type": "string",
          "enum": [
            "b10cm-pelpred",
            "b10cm",
            "csmall",
            "tpb",
            "bmed",
            "b30cm",
            "tc",
            "cmed",
            "b30cm-bendet",
            "tc10cm",
            "tc30cm",
            "b10cm-bendet",
            "bcom",
            "bsmall",
            "tcb",
            "tsb",
            "clarge",
            "blarge",
            "b30cm-pelpred"
          ]
        },
        "region": {
          "type": "string",
          "enum": [
            "global",
            "finland",
            "lena"
          ]
        },
        "time_step": {
          "type": "string",
          "enum": [
            "daily",
            "annual",
            "monthly"
          ]
        },
        "start_year": {
          "type": "number"
        },
        "end_year": {
          "type": "number"
        }
      }
    }
  }
}