{
  "$schema": "http://json-schema.org/draft-07/schema#",
  "$id": "https://protocol.isimip.org/schema/schema/ISIMIP2b/OutputData/marine-fishery_regional.json",
  "commit": "49732375ddbe9f178fe9fa06e30f6a5183b73d27",
  "type": "object",
  "required": [
    "specifiers"
  ],
  "properties": {
    "specifiers": {
      "type": "object",
      "required": [
        "model",
        "climate_forcing",
        "bias_adjustment",
        "climate_scenario",
        "variable",
        "ocean_region",
        "time_step"
      ],
      "properties": {
        "model": {
          "type": "string",
          "enum": [
            "matsiro",
            "ecomag",
            "osmose_humboldt-n",
            "ewe_adriatic-sea",
            "forclim",
            "clm45",
            "hbv-pik",
            "flake-igb",
            "bioscen15-mem-gam",
            "swat-ufz",
            "ewe_med-glob",
            "hype",
            "epic-iiasa",
            "epic-boku-hg",
            "ewe_nw-med-sea",
            "swat-iitgn",
            "ewe_north-sea",
            "gepic-br",
            "air2water4par",
            "pdssat-pt",
            "mizer",
            "vic-cma",
            "clm-crop",
            "epic-boku",
            "lake",
            "iapras-dss",
            "swbm",
            "mpi-hm",
            "watergap3",
            "hbv-cma",
            "ewe_east-bass-strait",
            "cgms-wofost",
            "pdssat",
            "orchidee",
            "mylake",
            "epic-boku-br",
            "vic-nve-v2",
            "boats",
            "bioscen15-mem-gbm",
            "gepic",
            "jules-b1",
            "dbh",
            "gepic-p",
            "jules-es-55",
            "web-dhm-s",
            "papsim",
            "dlem",
            "epic-boku-pt",
            "orchidee-crop",
            "ways",
            "vic-hhu",
            "ewe_baltic-sea",
            "dbpm",
            "gotilwaplus",
            "lpjml",
            "bioscen15-sdm-gam",
            "prebas",
            "vic-iitgn",
            "air2water6par",
            "papsim-pm",
            "hbv-jlu",
            "hymod-ufz",
            "vip",
            "jules-w1",
            "lpj-guess",
            "pcr-globwb",
            "simstrat",
            "vic",
            "vic-lake",
            "swim-nve",
            "swat-cma",
            "albm",
            "swat-sggw",
            "prysbi2",
            "swat-uottawa",
            "swim-cma",
            "orchidee-dgvm",
            "apecosm",
            "epic-tamu",
            "caraib",
            "gepic-pm",
            "hymod-jlu",
            "3pg",
            "3pgn-bw",
            "basfor",
            "vegas",
            "3d-cmcc-fem",
            "cwatm",
            "pegasus",
            "ewe_cook-strait",
            "bioscen15-sdm-gbm",
            "3d-cmcc-cnr-bgc",
            "pepic",
            "macroecological",
            "swap",
            "ecoocean",
            "watergap2",
            "vic-nve",
            "swat-vub",
            "simstrat-uog",
            "swim-pik",
            "dbem",
            "h08",
            "visit",
            "wbd",
            "clm50",
            "hbv-iww",
            "glm",
            "mhm",
            "clm40",
            "atlantis_se-australia",
            "swat-tamu",
            "epic-boku-pe",
            "gotm",
            "landscape-dndc",
            "swim-nve-v2",
            "gepic-pt"
          ]
        },
        "climate_forcing": {
          "type": "string",
          "enum": [
            "gfdl-esm2m",
            "miroc5",
            "hadgem2-es",
            "cesm1-bgc",
            "ipsl-cm5a-lr"
          ]
        },
        "bias_adjustment": {
          "type": "string",
          "enum": [
            "ewembi",
            "nobc"
          ]
        },
        "climate_scenario": {
          "type": "string",
          "enum": [
            "rcp26",
            "rcp45",
            "picontrol",
            "2005co2",
            "rcp60",
            "rcp85",
            "2299rcp26",
            "historical"
          ]
        },
        "variable": {
          "type": "string",
          "enum": [
            "tsb",
            "bcom",
            "b10cm",
            "tc30cm",
            "tc10cm",
            "tc",
            "b30cm",
            "tla",
            "tcb"
          ]
        },
        "ocean_region": {
          "type": "string",
          "enum": [
            "hawaii",
            "cook-strait",
            "adriatic-sea",
            "humboldt-n",
            "benguela",
            "east-bass-strait",
            "baltic-sea",
            "nw-med-sea",
            "med-glob",
            "north-sea",
            "se-australia"
          ]
        },
        "time_step": {
          "type": "string",
          "enum": [
            "monthly",
            "daily",
            "annual"
          ]
        },
        "start_year": {
          "type": "number"
        },
        "end_year": {
          "type": "number"
        }
      }
    }
  }
}